{"link":{"aliases":["elink","discordlink","ediscordlink"],"description":"Generates a code to link your Minecraft account to Discord.","usage":"/\u003ccommand\u003e","usages":[{"usage":"/\u003ccommand\u003e","description":"Generates a code for the /link command on Discord"}]},"unlink":{"aliases":["eunlink","discordunlink","ediscordunlink"],"description":"Unlinks your Minecraft account from the currently linked Discord account.","usage":"/\u003ccommand\u003e","usages":[{"usage":"/\u003ccommand\u003e","description":"Unlinks your Minecraft account from the currently linked Discord account."}]}}